liumi_cli/__init__.py
liumi_cli/main.py
liumi_cli-5.1.4.dist-info/licenses/LICENSE
liumi_cli-5.1.4.dist-info/METADATA
liumi_cli-5.1.4.dist-info/WHEEL
liumi_cli-5.1.4.dist-info/entry_points.txt
liumi_cli-5.1.4.dist-info/top_level.txt
liumi_cli-5.1.4.dist-info/RECORD
