Metadata-Version: 2.4
Name: liumi-cli
Version: 5.1.4
Summary: The Legendary AI DevOps Interface Utility
Home-page: https://liumi.cloud/liu
Author: Liumi Corporation
Author-email: support@liumi.cloud
Classifier: Programming Language :: Python :: 3
Classifier: License :: Other/Proprietary License
Classifier: Operating System :: OS Independent
Requires-Python: >=3.7
License-File: LICENSE
Requires-Dist: typer
Requires-Dist: rich
Requires-Dist: pyfiglet
Requires-Dist: requests
Requires-Dist: google-genai
Requires-Dist: PyGithub
Dynamic: author
Dynamic: author-email
Dynamic: classifier
Dynamic: description
Dynamic: description-content-type
Dynamic: home-page
Dynamic: license-file
Dynamic: requires-dist
Dynamic: requires-python
Dynamic: summary
